disdial/__chat.py
disdial/__constants.py
disdial/__init__.py
disdial/__user_name.py
disdial/__utils.py
disdial/main.py
disdial/data/config.json
disdial/data/logs.txt
disdial-1.3.2.2.dist-info/LICENSE
disdial-1.3.2.2.dist-info/METADATA
disdial-1.3.2.2.dist-info/WHEEL
disdial-1.3.2.2.dist-info/entry_points.txt
disdial-1.3.2.2.dist-info/top_level.txt
disdial-1.3.2.2.dist-info/RECORD
