Metadata-Version: 2.1
Name: disdial
Version: 1.3.2.2
Summary: A terminal-based IRC-inspired package that enables users to chat on a single server with everyone..
Author: Arpit Sengar (arpy8)
Classifier: Programming Language :: Python :: 3
Classifier: License :: OSI Approved :: MIT License
Classifier: Operating System :: OS Independent
License-File: LICENSE
Requires-Dist: wheel
Requires-Dist: termcolor
Requires-Dist: setuptools
Requires-Dist: argparse
Requires-Dist: requests
Requires-Dist: pytz
Requires-Dist: datetime
Requires-Dist: keyboard
Requires-Dist: pyautogui
